[
    {
        "title": "Despite Everything (AI Shortfilm)",
        "description": "Despite Everything is a visual poem that explores the quiet moments of joy found in the midst of struggle.",
        "url": "http://youtube.com/watch?v=NxaVQ67XbiA",
        "logo": "assets/projects/Despite_Everything_Thumbnail.jpeg",
        "Tech": ["Nano Banana Pro", "Veo3.1", "Suno AI", "Eleven Labs", "VN"]
    },
    {
        "title": "Warranty Management System",
        "description": "A system to manage warranties efficiently using n8n workflows.",
        "url": "https://github.com/bewithaby/Warranty-Management-System-n8n",
        "logo": "assets/projects/warranty.png",
        "languages": ["n8n", "JavaScript", "HTML"]
    },
    {
        "title": "My Portfolio",
        "description": "The source code for this portfolio website.",
        "url": "https://bewithaby.github.io",
        "logo": "assets/projects/portfolio.png",
        "languages": ["HTML", "CSS", "JavaScript"]
    },
    {
        "title": "Personal Assistant",
        "description": "An autonomous Personal AI Assistant using n8n.",
        "url": "https://github.com/bewithaby/Personal-Assistant-n8n",
        "logo": "assets/projects/assistant.png",
        "languages": ["n8n", "JavaScript", "HTML"]
    }
]
